<?xml version="1.0" encoding="UTF-8"?>
<factura id="Comprobante" version="1.00">
  <infoTributaria>
    <ambiente>1</ambiente>
    <tipoEmision>1</tipoEmision>
    <razonSocial>WILSON MORALES</razonSocial>
    <nombreComercial>SELI LOGISTICS</nombreComercial>
    <ruc>1003640511001</ruc>
    <claveAcceso>0501202301100364051100110010010000000731234567813</claveAcceso>
    <codDoc>01</codDoc>
    <estab>001</estab>
    <ptoEmi>001</ptoEmi>
    <secuencial>PIJAL ALTO CALLE PRINCIPAL A 500MTR. DE LA PANAMERICANA</secuencial>
    <dirMatriz>PIJAL ALTO CALLE PRINCIPAL A 500MTR. DE LA PANAMERICANA</dirMatriz>
  </infoTributaria>
  <infoFactura>
    <fechaEmision/>
    <direccionEstablecimiento>DIRECCION ESTABLECIMIENTO</direccionEstablecimiento>
    <obligadoContabilidad>NO</obligadoContabilidad>
    <tipoIdentificacionComprador>05</tipoIdentificacionComprador>
    <razonSocialComprador>NOMBRE DEL COMPRADOR</razonSocialComprador>
    <identificacionComprador>1234567891</identificacionComprador>
    <totalSinImpuestos>181.79</totalSinImpuestos>
    <totalDescuento>0.00</totalDescuento>
    <totalConImpuestos/>
    <totalImpuesto/>
    <codigo>2</codigo>
    <codigoPorcentaje>0</codigoPorcentaje>
    <baseImponible>1.00</baseImponible>
    <valor>0</valor>
    <propina>0.00</propina>
    <importeTotal>0.00</importeTotal>
    <moneda>DOLAR</moneda>
    <pagos>
      <pago>
        <formaPago>01</formaPago>
        <total>203.60</total>
        <plazo>30</plazo>
        <unidadTiempo>dias</unidadTiempo>
      </pago>
    </pagos>
  </infoFactura>
  <detalles>
    <detalle>
      <codigoPrincipal>PROD008</codigoPrincipal>
      <descripcion>DESCRIPCION DEL PRODUCTO</descripcion>
      <cantidad>1</cantidad>
      <precioUnitario>1.00</precioUnitario>
      <descuento>0.00</descuento>
      <precioTotal>1.00</precioTotal>
    </detalle>
  </detalles>
  <infoAdicional>
    <campoAdicional nombre="email">xyz@xyz.com</campoAdicional>
  </infoAdicional>
</factura>
